pysectools/__init__.py
pysectools/pinentry.py
pysectools-0.5.2.dist-info/METADATA
pysectools-0.5.2.dist-info/WHEEL
pysectools-0.5.2.dist-info/top_level.txt
pysectools-0.5.2.dist-info/RECORD
