Metadata-Version: 2.1
Name: pysectools
Version: 0.5.2
Summary: A package of security-related Python functions. Dropping
Home-page: https://github.com/myfreeweb/pysectools
Author: Greg V
Author-email: greg@unrelenting.technology
License: Unlicense
Keywords: security,pinentry,getpass,capsicum,random,rng,arc4random
Platform: UNKNOWN
Classifier: Operating System :: POSIX
Classifier: Intended Audience :: Developers
Classifier: Programming Language :: Python
Classifier: License :: Public Domain
Classifier: Topic :: Security
